ytsage/__init__.py
ytsage/main.py
ytsage/assets/Icon/icon.png
ytsage/assets/sound/notification.mp3
ytsage/languages/ar.json
ytsage/languages/de.json
ytsage/languages/en.json
ytsage/languages/es.json
ytsage/languages/fr.json
ytsage/languages/hi.json
ytsage/languages/id.json
ytsage/languages/it.json
ytsage/languages/ja.json
ytsage/languages/pl.json
ytsage/languages/pt.json
ytsage/languages/ru.json
ytsage/languages/tr.json
ytsage/languages/zh.json
ytsage/src/__init__.py
ytsage/src/core/__init__.py
ytsage/src/core/ytsage_deno.py
ytsage/src/core/ytsage_downloader.py
ytsage/src/core/ytsage_ffmpeg.py
ytsage/src/core/ytsage_utils.py
ytsage/src/core/ytsage_yt_dlp.py
ytsage/src/gui/__init__.py
ytsage/src/gui/ytsage_gui_format_table.py
ytsage/src/gui/ytsage_gui_main.py
ytsage/src/gui/ytsage_gui_video_info.py
ytsage/src/gui/ytsage_gui_dialogs/__init__.py
ytsage/src/gui/ytsage_gui_dialogs/ytsage_dialogs_base.py
ytsage/src/gui/ytsage_gui_dialogs/ytsage_dialogs_custom.py
ytsage/src/gui/ytsage_gui_dialogs/ytsage_dialogs_ffmpeg.py
ytsage/src/gui/ytsage_gui_dialogs/ytsage_dialogs_history.py
ytsage/src/gui/ytsage_gui_dialogs/ytsage_dialogs_selection.py
ytsage/src/gui/ytsage_gui_dialogs/ytsage_dialogs_settings.py
ytsage/src/gui/ytsage_gui_dialogs/ytsage_dialogs_update.py
ytsage/src/gui/ytsage_gui_dialogs/ytsage_dialogs_updater.py
ytsage/src/utils/__init__.py
ytsage/src/utils/ytsage_config_manager.py
ytsage/src/utils/ytsage_constants.py
ytsage/src/utils/ytsage_history_manager.py
ytsage/src/utils/ytsage_localization.py
ytsage/src/utils/ytsage_logger.py
ytsage-4.9.7.dist-info/licenses/LICENSE
ytsage-4.9.7.dist-info/METADATA
ytsage-4.9.7.dist-info/WHEEL
ytsage-4.9.7.dist-info/entry_points.txt
ytsage-4.9.7.dist-info/top_level.txt
ytsage-4.9.7.dist-info/RECORD
