Metadata-Version: 2.4
Name: ytsage
Version: 4.9.7
Summary: Modern YouTube downloader with a clean PySide6 interface.
Home-page: https://github.com/oop7/YTSage
Author: oop7
Author-email: oop7 <oop7_support@proton.me>
License: MIT License
Project-URL: Homepage, https://github.com/oop7/YTSage
Project-URL: Bug-Tracker, https://github.com/oop7/YTSage/issues
Project-URL: Reddit, https://www.reddit.com/r/NO-N_A_M_E/
Keywords: youtube,downloader,video,audio,PySide6,yt-dlp,GUI
Classifier: Development Status :: 5 - Production/Stable
Classifier: Programming Language :: Python :: 3
Classifier: Programming Language :: Python :: 3.10
Classifier: Programming Language :: Python :: 3.11
Classifier: Programming Language :: Python :: 3.12
Classifier: Programming Language :: Python :: 3.13
Classifier: Programming Language :: Python :: 3.14
Classifier: License :: OSI Approved :: MIT License
Classifier: Intended Audience :: End Users/Desktop
Classifier: Operating System :: OS Independent
Classifier: Operating System :: Microsoft :: Windows
Classifier: Operating System :: POSIX :: Linux
Classifier: Operating System :: MacOS
Classifier: Topic :: Internet :: WWW/HTTP
Classifier: Topic :: Multimedia :: Video
Classifier: Topic :: Multimedia :: Sound/Audio
Classifier: Topic :: Desktop Environment
Classifier: Environment :: X11 Applications :: Qt
Classifier: Environment :: Win32 (MS Windows)
Classifier: Environment :: MacOS X
Requires-Python: >=3.10,<3.15
License-File: LICENSE
Requires-Dist: PySide6>=6.10.1
Requires-Dist: requests>=2.32.5
Requires-Dist: pillow>=12.0.0
Requires-Dist: packaging>=25.0
Requires-Dist: markdown>=3.10
Requires-Dist: pyglet>=2.1.11
Requires-Dist: loguru>=0.7.3
Requires-Dist: setuptools>=80.9.0
Dynamic: author
Dynamic: home-page
Dynamic: license-file
Dynamic: requires-python
